geestac/__init__.py
geestac/bands.py
geestac/catalog.py
geestac/custom_types.py
geestac/dataset.py
geestac/feature_collection.py
geestac/helpers.py
geestac/image.py
geestac/image_collection.py
geestac/py.typed
geestac/stac.py
geestac-0.0.1.dist-info/METADATA
geestac-0.0.1.dist-info/WHEEL
geestac-0.0.1.dist-info/licenses/AUTHORS.rst
geestac-0.0.1.dist-info/licenses/LICENSE
geestac-0.0.1.dist-info/RECORD
