Metadata-Version: 2.4
Name: geestac
Version: 0.0.1
Summary: Google Earth Engine STAC
Project-URL: Homepage, https://github.com/fitoprincipe/geestac
Author-email: Rodrigo Esteban Principe <fitoprincipe82@gmail.com>
License: MIT
License-File: AUTHORS.rst
License-File: LICENSE
Keywords: Google Earth Engine,Python,STAC,geetools,skeleton
Classifier: Development Status :: 3 - Alpha
Classifier: Intended Audience :: Developers
Classifier: License :: OSI Approved :: MIT License
Classifier: Programming Language :: Python :: 3.8
Classifier: Programming Language :: Python :: 3.9
Classifier: Programming Language :: Python :: 3.10
Classifier: Programming Language :: Python :: 3.11
Requires-Python: >=3.10
Requires-Dist: deprecated>=1.2.14
Requires-Dist: earthengine-api
Requires-Dist: requests
Provides-Extra: doc
Requires-Dist: pydata-sphinx-theme; extra == 'doc'
Requires-Dist: sphinx-autoapi; extra == 'doc'
Requires-Dist: sphinx-copybutton; extra == 'doc'
Requires-Dist: sphinx-design; extra == 'doc'
Requires-Dist: sphinx>=6.2.1; extra == 'doc'
Provides-Extra: test
Requires-Dist: pytest; extra == 'test'
Requires-Dist: pytest-cov; extra == 'test'
Requires-Dist: pytest-deadfixtures; extra == 'test'
